Metadata-Version: 2.1
Name: odoo10-addon-event-sale-registration-multi-qty
Version: 10.0.1.0.0.99.dev2
Summary: Allows sell registrations with more than one attendee
Home-page: https://www.tecnativa.com
Author: Tecnativa, Odoo Community Association (OCA)
Author-email: support@odoo-community.org
License: AGPL-3
Platform: UNKNOWN
Classifier: Programming Language :: Python
Classifier: Framework :: Odoo
Classifier: License :: OSI Approved :: GNU Affero General Public License v3
Requires-Python: ~=2.7
Requires-Dist: odoo10-addon-event-registration-multi-qty
Requires-Dist: odoo (<10.1dev,>=10.0)
